evalassist/__init__.py
evalassist/actions_logger.py
evalassist/alembic/README
evalassist/alembic/env.py
evalassist/alembic/script.py.mako
evalassist/alembic/versions/004150514536_add_user_id_to_log_record.py
evalassist/alembic/versions/6da8778318cb_init.py
evalassist/alembic.ini
evalassist/api_types.py
evalassist/benchmark/__init__.py
evalassist/benchmark/benchmark.py
evalassist/benchmark/benchmark_results.db
evalassist/benchmark/run_benchmarks.py
evalassist/benchmark/utils.py
evalassist/cli.py
evalassist/const.py
evalassist/database.py
evalassist/extended_unitxt.py
evalassist/judges/README.md
evalassist/judges/__init__.py
evalassist/judges/base.py
evalassist/judges/batch_repair_parser.py
evalassist/judges/const.py
evalassist/judges/direct_judge.py
evalassist/judges/dummy_judge.py
evalassist/judges/experimental/criticized_judge.py
evalassist/judges/experimental/thesis_antithesis_direct_judge.py
evalassist/judges/granite_guardian_judge.py
evalassist/judges/mprometheus_judge.py
evalassist/judges/pairwise_judge.py
evalassist/judges/types.py
evalassist/judges/unitxt_judges.py
evalassist/judges/utils.py
evalassist/main.py
evalassist/model.py
evalassist/notebook_generation.py
evalassist/static/404/index.html
evalassist/static/404.html
evalassist/static/_next/static/5j5uG_Un6v-o5faVCwJXY/_buildManifest.js
evalassist/static/_next/static/5j5uG_Un6v-o5faVCwJXY/_ssgManifest.js
evalassist/static/_next/static/chunks/472-9ebf9024bc039b81.js
evalassist/static/_next/static/chunks/808-ba05144b7460a1cd.js
evalassist/static/_next/static/chunks/818-50255d3da5031c79.js
evalassist/static/_next/static/chunks/framework-144ddb6b9c2105c7.js
evalassist/static/_next/static/chunks/main-8fad050eb1302c48.js
evalassist/static/_next/static/chunks/pages/_app-2a1d11c33a06fe67.js
evalassist/static/_next/static/chunks/pages/_error-7a92967bea80186d.js
evalassist/static/_next/static/chunks/pages/benchmarks-5e7a4d2f1223ad77.js
evalassist/static/_next/static/chunks/pages/index-235bdf9d19b1f814.js
evalassist-1.0.3.dist-info/METADATA
evalassist-1.0.3.dist-info/WHEEL
evalassist-1.0.3.dist-info/entry_points.txt
evalassist-1.0.3.dist-info/RECORD
